manifold/__init__.py
manifold/hub/__init__.py
manifold/hub/main.py
manifold/hub/modules/node.py
manifold/hub/routers/__init__.py
manifold/hub/routers/general_router.py
manifold/hub/routers/node_router.py
manifold/hub/src/node/node_cleanup.py
manifold/hub/src/node/node_launch.py
manifold/hub/src/node/api/node.py
manifold/hub/src/node/utils/port_lookup.py
manifold/node/__init__.py
manifold/node/main.py
manifold/node/modules/__init__.py
manifold/node/modules/endpoint.py
manifold/node/routers/__init__.py
manifold/node/routers/general_node_router.py
manifoldx-0.1.0.dist-info/METADATA
manifoldx-0.1.0.dist-info/WHEEL
manifoldx-0.1.0.dist-info/top_level.txt
manifoldx-0.1.0.dist-info/RECORD
