Metadata-Version: 2.4
Name: manifoldx
Version: 0.1.0
Summary: A Python package for building & running AI app node
Author: Manifold Team
License: MIT
Requires-Python: >=3.6
Requires-Dist: docker>=6.1.3
Requires-Dist: fastapi>=0.104.1
Requires-Dist: gradio>=4.19.2
Requires-Dist: torch>=2.1.0
Requires-Dist: uvicorn>=0.24.0
Requires-Dist: requests>=2.31.0
Requires-Dist: fastapi-mcp==0.2.0
